gufo/thor/__init__.py
gufo/thor/cli.py
gufo/thor/config.py
gufo/thor/docker.py
gufo/thor/error.py
gufo/thor/ip.py
gufo/thor/log.py
gufo/thor/py.typed
gufo/thor/secret.py
gufo/thor/utils.py
gufo/thor/validator.py
gufo/thor/labs/__init__.py
gufo/thor/labs/base.py
gufo/thor/labs/vyos.py
gufo/thor/samples/common.yml
gufo/thor/samples/lab1.yml
gufo/thor/samples/simple.yml
gufo/thor/services/__init__.py
gufo/thor/services/activator.py
gufo/thor/services/auth.py
gufo/thor/services/base.py
gufo/thor/services/bh.py
gufo/thor/services/bi.py
gufo/thor/services/card.py
gufo/thor/services/chwriter.py
gufo/thor/services/classifier.py
gufo/thor/services/clickhouse.py
gufo/thor/services/consul.py
gufo/thor/services/correlator.py
gufo/thor/services/datasource.py
gufo/thor/services/datastream.py
gufo/thor/services/discovery.py
gufo/thor/services/envoy.py
gufo/thor/services/escalator.py
gufo/thor/services/grafanads.py
gufo/thor/services/icqsender.py
gufo/thor/services/kafka.py
gufo/thor/services/kafkasender.py
gufo/thor/services/login.py
gufo/thor/services/mailsender.py
gufo/thor/services/metrics.py
gufo/thor/services/metricscollector.py
gufo/thor/services/mib.py
gufo/thor/services/migrate.py
gufo/thor/services/mongo.py
gufo/thor/services/mrt.py
gufo/thor/services/mx.py
gufo/thor/services/nbi.py
gufo/thor/services/noc.py
gufo/thor/services/ping.py
gufo/thor/services/postgres.py
gufo/thor/services/runner.py
gufo/thor/services/sae.py
gufo/thor/services/scheduler.py
gufo/thor/services/selfmon.py
gufo/thor/services/shell.py
gufo/thor/services/static.py
gufo/thor/services/syslogcollector.py
gufo/thor/services/tgsender.py
gufo/thor/services/topo.py
gufo/thor/services/trapcollector.py
gufo/thor/services/ui.py
gufo/thor/services/web.py
gufo/thor/services/worker.py
gufo/thor/services/zeroconf.py
gufo/thor/targets/__init__.py
gufo/thor/targets/base.py
gufo/thor/targets/compose.py
gufo/thor/templates/envoy/envoy.yaml
gufo/thor/templates/labs/vyos/config.boot.j2
gufo_thor-0.11.0.dist-info/licenses/LICENSE.md
gufo_thor-0.11.0.dist-info/METADATA
gufo_thor-0.11.0.dist-info/WHEEL
gufo_thor-0.11.0.dist-info/entry_points.txt
gufo_thor-0.11.0.dist-info/top_level.txt
gufo_thor-0.11.0.dist-info/RECORD
